TongguoLiziXueRustFix1/README.md
TongguoLiziXueRustFix1/__init__.py
TongguoLiziXueRustFix1/__main__.py
TongguoLiziXueRustFix1/file.epub
TongguoLiziXueRustFix1/index.html
TongguoLiziXueRustFix1/css/__init__.py
TongguoLiziXueRustFix1/css/annotations.css
TongguoLiziXueRustFix1/css/main.css
TongguoLiziXueRustFix1/css/normalize.css
TongguoLiziXueRustFix1/css/popup.css
TongguoLiziXueRustFix1/font/__init__.py
TongguoLiziXueRustFix1/font/fontello.eot
TongguoLiziXueRustFix1/font/fontello.svg
TongguoLiziXueRustFix1/font/fontello.ttf
TongguoLiziXueRustFix1/font/fontello.woff
TongguoLiziXueRustFix1/img/__init__.py
TongguoLiziXueRustFix1/img/annotator-glyph-sprite.png
TongguoLiziXueRustFix1/img/annotator-icon-sprite.png
TongguoLiziXueRustFix1/img/apple-touch-icon.png
TongguoLiziXueRustFix1/img/cancelfullscreen.png
TongguoLiziXueRustFix1/img/close.png
TongguoLiziXueRustFix1/img/fullscreen.png
TongguoLiziXueRustFix1/img/loader.gif
TongguoLiziXueRustFix1/img/menu-icon.png
TongguoLiziXueRustFix1/img/save.png
TongguoLiziXueRustFix1/img/saved.png
TongguoLiziXueRustFix1/img/settings-s.png
TongguoLiziXueRustFix1/img/settings.png
TongguoLiziXueRustFix1/img/star.png
TongguoLiziXueRustFix1/js/__init__.py
TongguoLiziXueRustFix1/js/epub.js
TongguoLiziXueRustFix1/js/epub.min.js
TongguoLiziXueRustFix1/js/epub.min.map
TongguoLiziXueRustFix1/js/hooks.min.js
TongguoLiziXueRustFix1/js/hooks.min.map
TongguoLiziXueRustFix1/js/reader.js
TongguoLiziXueRustFix1/js/reader.js.map
TongguoLiziXueRustFix1/js/reader.min.js
TongguoLiziXueRustFix1/js/reader.min.map
TongguoLiziXueRustFix1/js/hooks/__init__.py
TongguoLiziXueRustFix1/js/hooks/extensions/__init__.py
TongguoLiziXueRustFix1/js/hooks/extensions/highlight.js
TongguoLiziXueRustFix1/js/libs/__init__.py
TongguoLiziXueRustFix1/js/libs/jquery.min.js
TongguoLiziXueRustFix1/js/libs/localforage.min.js
TongguoLiziXueRustFix1/js/libs/screenfull.js
TongguoLiziXueRustFix1/js/libs/screenfull.min.js
TongguoLiziXueRustFix1/js/libs/zip.min.js
tongguo_lizi_xue_rust_fix1-2025.3.25.0.dist-info/METADATA
tongguo_lizi_xue_rust_fix1-2025.3.25.0.dist-info/WHEEL
tongguo_lizi_xue_rust_fix1-2025.3.25.0.dist-info/entry_points.txt
tongguo_lizi_xue_rust_fix1-2025.3.25.0.dist-info/top_level.txt
tongguo_lizi_xue_rust_fix1-2025.3.25.0.dist-info/RECORD
